colorgram_rust-0.2.0.dist-info/METADATA
colorgram_rust-0.2.0.dist-info/WHEEL
colorgram_rust.libs/libcrypto-b24afd48.so.3
colorgram_rust.libs/libssl-57118d4e.so.3
colorgram_rust/__init__.py
colorgram_rust/colorgram_rust.cpython-310-x86_64-linux-gnu.so
colorgram_rust-0.2.0.dist-info/RECORD
